{"trial_id": "01", "hyperparameters": {"space": [{"class_name": "Int", "config": {"name": "num_layers_conv", "default": null, "conditions": [], "min_value": 1, "max_value": 6, "step": 1, "sampling": "linear"}}, {"class_name": "Float", "config": {"name": "learning_rate", "default": 0.0001, "conditions": [], "min_value": 0.0001, "max_value": 0.01, "step": null, "sampling": "log"}}, {"class_name": "Int", "config": {"name": "units_conv0", "default": null, "conditions": [], "min_value": 1, "max_value": 15, "step": 1, "sampling": "linear"}}, {"class_name": "Choice", "config": {"name": "activation_conv0", "default": "relu", "conditions": [], "values": ["relu", "tanh"], "ordered": false}}, {"class_name": "Choice", "config": {"name": "kernel_0", "default": 2, "conditions": [], "values": [2, 3, 4, 5], "ordered": true}}, {"class_name": "Float", "config": {"name": "l2_conv0", "default": 0.0, "conditions": [], "min_value": 0.0, "max_value": 0.01, "step": 0.001, "sampling": "linear"}}, {"class_name": "Int", "config": {"name": "num_layers_fully", "default": null, "conditions": [], "min_value": 1, "max_value": 6, "step": 1, "sampling": "linear"}}, {"class_name": "Int", "config": {"name": "units_dense0", "default": null, "conditions": [], "min_value": 32, "max_value": 512, "step": 32, "sampling": "linear"}}, {"class_name": "Choice", "config": {"name": "activation_dense0", "default": "relu", "conditions": [], "values": ["relu", "tanh"], "ordered": false}}, {"class_name": "Float", "config": {"name": "l2_dense0", "default": 0.0, "conditions": [], "min_value": 0.0, "max_value": 0.01, "step": 0.001, "sampling": "linear"}}, {"class_name": "Int", "config": {"name": "units_conv1", "default": null, "conditions": [], "min_value": 1, "max_value": 15, "step": 1, "sampling": "linear"}}, {"class_name": "Choice", "config": {"name": "activation_conv1", "default": "relu", "conditions": [], "values": ["relu", "tanh"], "ordered": false}}, {"class_name": "Choice", "config": {"name": "kernel_1", "default": 2, "conditions": [], "values": [2, 3, 4, 5], "ordered": true}}, {"class_name": "Float", "config": {"name": "l2_conv1", "default": 0.0, "conditions": [], "min_value": 0.0, "max_value": 0.01, "step": 0.001, "sampling": "linear"}}, {"class_name": "Int", "config": {"name": "units_conv2", "default": null, "conditions": [], "min_value": 1, "max_value": 15, "step": 1, "sampling": "linear"}}, {"class_name": "Choice", "config": {"name": "activation_conv2", "default": "relu", "conditions": [], "values": ["relu", "tanh"], "ordered": false}}, {"class_name": "Choice", "config": {"name": "kernel_2", "default": 2, "conditions": [], "values": [2, 3, 4, 5], "ordered": true}}, {"class_name": "Float", "config": {"name": "l2_conv2", "default": 0.0, "conditions": [], "min_value": 0.0, "max_value": 0.01, "step": 0.001, "sampling": "linear"}}, {"class_name": "Int", "config": {"name": "units_conv3", "default": null, "conditions": [], "min_value": 1, "max_value": 15, "step": 1, "sampling": "linear"}}, {"class_name": "Choice", "config": {"name": "activation_conv3", "default": "relu", "conditions": [], "values": ["relu", "tanh"], "ordered": false}}, {"class_name": "Choice", "config": {"name": "kernel_3", "default": 2, "conditions": [], "values": [2, 3, 4, 5], "ordered": true}}, {"class_name": "Float", "config": {"name": "l2_conv3", "default": 0.0, "conditions": [], "min_value": 0.0, "max_value": 0.01, "step": 0.001, "sampling": "linear"}}, {"class_name": "Int", "config": {"name": "units_conv4", "default": null, "conditions": [], "min_value": 1, "max_value": 15, "step": 1, "sampling": "linear"}}, {"class_name": "Choice", "config": {"name": "activation_conv4", "default": "relu", "conditions": [], "values": ["relu", "tanh"], "ordered": false}}, {"class_name": "Choice", "config": {"name": "kernel_4", "default": 2, "conditions": [], "values": [2, 3, 4, 5], "ordered": true}}, {"class_name": "Float", "config": {"name": "l2_conv4", "default": 0.0, "conditions": [], "min_value": 0.0, "max_value": 0.01, "step": 0.001, "sampling": "linear"}}, {"class_name": "Int", "config": {"name": "units_dense1", "default": null, "conditions": [], "min_value": 32, "max_value": 512, "step": 32, "sampling": "linear"}}, {"class_name": "Choice", "config": {"name": "activation_dense1", "default": "relu", "conditions": [], "values": ["relu", "tanh"], "ordered": false}}, {"class_name": "Float", "config": {"name": "l2_dense1", "default": 0.0, "conditions": [], "min_value": 0.0, "max_value": 0.01, "step": 0.001, "sampling": "linear"}}, {"class_name": "Int", "config": {"name": "units_dense2", "default": null, "conditions": [], "min_value": 32, "max_value": 512, "step": 32, "sampling": "linear"}}, {"class_name": "Choice", "config": {"name": "activation_dense2", "default": "relu", "conditions": [], "values": ["relu", "tanh"], "ordered": false}}, {"class_name": "Float", "config": {"name": "l2_dense2", "default": 0.0, "conditions": [], "min_value": 0.0, "max_value": 0.01, "step": 0.001, "sampling": "linear"}}, {"class_name": "Int", "config": {"name": "units_dense3", "default": null, "conditions": [], "min_value": 32, "max_value": 512, "step": 32, "sampling": "linear"}}, {"class_name": "Choice", "config": {"name": "activation_dense3", "default": "relu", "conditions": [], "values": ["relu", "tanh"], "ordered": false}}, {"class_name": "Float", "config": {"name": "l2_dense3", "default": 0.0, "conditions": [], "min_value": 0.0, "max_value": 0.01, "step": 0.001, "sampling": "linear"}}, {"class_name": "Int", "config": {"name": "units_dense4", "default": null, "conditions": [], "min_value": 32, "max_value": 512, "step": 32, "sampling": "linear"}}, {"class_name": "Choice", "config": {"name": "activation_dense4", "default": "relu", "conditions": [], "values": ["relu", "tanh"], "ordered": false}}, {"class_name": "Float", "config": {"name": "l2_dense4", "default": 0.0, "conditions": [], "min_value": 0.0, "max_value": 0.01, "step": 0.001, "sampling": "linear"}}, {"class_name": "Int", "config": {"name": "units_dense5", "default": null, "conditions": [], "min_value": 32, "max_value": 512, "step": 32, "sampling": "linear"}}, {"class_name": "Choice", "config": {"name": "activation_dense5", "default": "relu", "conditions": [], "values": ["relu", "tanh"], "ordered": false}}, {"class_name": "Float", "config": {"name": "l2_dense5", "default": 0.0, "conditions": [], "min_value": 0.0, "max_value": 0.01, "step": 0.001, "sampling": "linear"}}], "values": {"num_layers_conv": 4, "learning_rate": 0.00013971810822965757, "units_conv0": 14, "activation_conv0": "relu", "kernel_0": 5, "l2_conv0": 0.004, "num_layers_fully": 1, "units_dense0": 448, "activation_dense0": "tanh", "l2_dense0": 0.01, "units_conv1": 3, "activation_conv1": "relu", "kernel_1": 2, "l2_conv1": 0.0, "units_conv2": 3, "activation_conv2": "tanh", "kernel_2": 4, "l2_conv2": 0.001, "units_conv3": 10, "activation_conv3": "relu", "kernel_3": 4, "l2_conv3": 0.009000000000000001, "units_conv4": 5, "activation_conv4": "relu", "kernel_4": 2, "l2_conv4": 0.0, "units_dense1": 384, "activation_dense1": "relu", "l2_dense1": 0.005, "units_dense2": 128, "activation_dense2": "relu", "l2_dense2": 0.003, "units_dense3": 32, "activation_dense3": "relu", "l2_dense3": 0.01, "units_dense4": 192, "activation_dense4": "tanh", "l2_dense4": 0.009000000000000001, "units_dense5": 32, "activation_dense5": "tanh", "l2_dense5": 0.008}}, "metrics": {"metrics": {"Verstellweg_Phi_loss": {"direction": "min", "observations": [{"value": [0.6831971406936646], "step": 1}]}, "Verstellweg_Phi_mae": {"direction": "min", "observations": [{"value": [0.6831066012382507], "step": 1}]}, "Verstellweg_X_loss": {"direction": "min", "observations": [{"value": [0.183783620595932], "step": 1}]}, "Verstellweg_X_mae": {"direction": "min", "observations": [{"value": [0.18388165533542633], "step": 1}]}, "Verstellweg_Y_loss": {"direction": "min", "observations": [{"value": [1.9312084913253784], "step": 1}]}, "Verstellweg_Y_mae": {"direction": "min", "observations": [{"value": [1.9307876825332642], "step": 1}]}, "loss": {"direction": "min", "observations": [{"value": [3.010411262512207], "step": 1}]}, "val_Verstellweg_Phi_loss": {"direction": "min", "observations": [{"value": [0.5842906832695007], "step": 1}]}, "val_Verstellweg_Phi_mae": {"direction": "min", "observations": [{"value": [0.5843039751052856], "step": 1}]}, "val_Verstellweg_X_loss": {"direction": "min", "observations": [{"value": [0.5563179850578308], "step": 1}]}, "val_Verstellweg_X_mae": {"direction": "min", "observations": [{"value": [0.5559278130531311], "step": 1}]}, "val_Verstellweg_Y_loss": {"direction": "min", "observations": [{"value": [1.4036513566970825], "step": 1}]}, "val_Verstellweg_Y_mae": {"direction": "min", "observations": [{"value": [1.4034016132354736], "step": 1}]}, "val_loss": {"direction": "min", "observations": [{"value": [2.738420009613037], "step": 1}]}}}, "score": 2.738420009613037, "best_step": 1, "status": "COMPLETED", "message": null}